dr_data/__init__.py
dr_data/main.py
dr_data/static_strings.py
dr_data/biopsy/__init__.py
dr_data/inject/__init__.py
dr_data/randoms/__init__.py
dr_data/sql/__init__.py
dr_data/transplant/__init__.py
dr_data/utilities/__init__.py
dr_data/utilities/db.py
dr_data/utilities/file.py
dr_data-1.0.1.dist-info/LICENSE.txt
dr_data-1.0.1.dist-info/METADATA
dr_data-1.0.1.dist-info/WHEEL
dr_data-1.0.1.dist-info/entry_points.txt
dr_data-1.0.1.dist-info/top_level.txt
dr_data-1.0.1.dist-info/RECORD
