Metadata-Version: 2.1
Name: dr-data
Version: 1.0.1
Summary: This is a database utility tool that can populate random data based on your schema or can import custom CSV data.
Home-page: https://github.com/sunnysidesounds/dr_data
Author: Jason R Alexander
Author-email: sunysidesounds@gmail.com
License: MIT
Project-URL: Documentation, https://dr-data.readthedocs.io/en/latest/
Platform: any
Classifier: Development Status :: 4 - Beta
Classifier: Programming Language :: Python
License-File: LICENSE.txt
Requires-Dist: importlib-metadata
Requires-Dist: python-version (<3.8)
Requires-Dist: faker
Requires-Dist: psycopg2-binary
Requires-Dist: pandas
Requires-Dist: progress
Provides-Extra: testing
Requires-Dist: setuptools ; extra == 'testing'
Requires-Dist: pytest ; extra == 'testing'
Requires-Dist: pytest-cov ; extra == 'testing'
Requires-Dist: psycopg2-binary ; extra == 'testing'
Requires-Dist: testing.postgresql ; extra == 'testing'
